{"mission_jaq_treasure":"The Thieves","mission_cas_relic":"Join of Lyndon","test_zone":"Test Zone","map_size_reference":"Test Size","barrack02":"Office of Pioneer Support","reb_basic":"Cite de Reboldoeux","barrack":"Barrack","coim_basic_tuto":"Port of Coimbra (Tutorial)","coim_basic":"The Port of Coimbra","reb_itemshop":"Room of Operator","gm_event_zone":"Event Zone","city_tuto":"Startonia","screenshot_zone":"Screenshot Zone","beraroom":"Cano's Room","arm_basic":"Armonia","dun_arm01_movie01":"Armonia, Basement Cathedral Video","arm_cathedral":"Armonia Cathedral","fld_arm":"Armonia, Anilio","btl_arm01":"Armonia, Latina","dun_arm01":"Armonia, En Celar","arm_apostadero":"Armonia, Apostadero","dun_arm02":"Armonia, El Templo","dun_arm03":"Armonia, Gloria","dun_arm04":"Armonia, Biego","dun_arm05_blue":"Armonia, El Soltado","dun_arm05_red":"Armonia, El Adio","dun_caslucifer04":"The Lucifer Castle, the Reception Hall of Oblivion","dun_clocktower02_10_boss":"Truman's Secret Laboratory","dun_trm01":"Truman's Secret Workshop B1F","dun_clocktower02_01":"Clock Tower Basement Lobby","bedel_basic":"Bedel","btl_bedel01":"Bedel Plain","fld_ile01":"Vernier Mansion, Entrance","dun_ile01":"Vernier Mainsion, 1st Floor","dun_ile02":"Vernier Mansion 2nd Floor","ile_basic":"Illisia","fld_ile02":"Royal Road","dun_casile01":"Distorted time : Imperium Arma","dun_casile02":"Distorted time : Imperium Rex","dun_casile03":"The Distorted time: Imperium Glory","mission_skyRoad_star":"Wreckage of Heaven Way","reb_wepshop":"Master Room of Reboldoeux","party_hq":"Reboldoeux Reception Hall 1","city_frourio":"Prurio","frourio_cave":"Burlon's Hideout","fld_alt01":"Camellia Thea","fld_alt02":"River of Fire","portus_basic":"Portus","btl_romanruin":"Ruina","dun_qiritatio01":"Quiritatio, Haimdar","dun_einheri01":"Quiritatio, Einheri","fld_reb":"Gate of Reboldoeux Queen","fld_ttr":"Tetra Ruins","fld_ptv":"Porto Bello","fld_alq":"Al Quelt Moreza","fld_coim":"Coimbra Nimrod Bridge","fld_coim_tuto":"The Nimrod Bridge(Tutorial)","auch_basic":"Auch (WCC)","fld_auch":"Thueringen Lakeside (WCC)","btl_ttr02":"Garden of the King (WCC)","btl_coim01":"Jezebel Glen (WCC)","btl_reb02":"The Bonavista River (WCC)","btl_reb03":"The Rion Plain (WCC)","btl_reb04":"The Ferruccio Junction (WCC)","btl_ptv01":"Deserted Quay of Porto Bello (WCC)","btl_reb05":"Lago Celeste (WCC)","btl_auch03":"El Tejado Verde (WCC)","btl_auch02":"El Lago de Tres Hermanas (WCC)","fld_anotherarm":"Distorted Armonia","ctd_basic":"Distorted Armonia, Cathedral","btl_reb01":"Reboldoeux Stone Pit","btl_ttr01":"Tetra Hill","btl_alq01":"Cathari Falls","btl_ttr03":"Topolo Durga","arena_city":"Training Center of Soldier of Reboldoeux","saint_zone":"St. Maria","tuto_room":"Office of Pioneer Support","saint_base":"St. Maria Cabin","water_room":"water_room","fld_ruin":"fld_ruin","lobby":"lobby","4s_map":"4s_map","field_e":"field_e","fld_portus":"fld_portus","btl_reb06":"Vegas Javier","btl_auch01":"Thueringenwald","ust_basic":"Ustiur, Base Camp","ust_farm":"Ustiur, The Farm","btl_ust01":"Ustiur, Ustiur Jungle Area 1","btl_ust02":"Ustiur, Ustiur Jungle Area 2","btl_ust03":"Ustiur, Ustiur Jungle Area 3","btl_ust04":"Ustiur, Ustiur Jungle Area 4","pinta_zone":"The Ustiur-Coimbra ferry boat, the Pinta","mission_rafflesia":"Rafflesia","dun_jaq01":"Jaquin, The Mohrgus","dun_jaq_c01":"Jaquin, Altar of Despair","dun_jaq05":"Jaquin, Torture Chamber","dun_jaq03":"Jaquin, Schivarliere","dun_jaq_c04":"Jaquin, Gehenna Bridge","dun_jaq06":"Jaquin, Laboratory Block","fld_jaq":"Lava Plateau of Jaquin","btl_jaq01":"Crater of Jaquin","btl_jaq03":"El Canon de Diabolica","btl_jaq04":"El Ruina de Memoria","mission_chainrush":"Whirlpool of Flame","btl_jaq02":"Pradera de Ceniza","dun_jaq_boss":"Jaquin, Corridor of Assize","btl_prison01":"Sacred Dungeon","btl_prison02":"Underground Prison 1F","dun_tor01":"M. Dr.Torsche, Reception Hall","dun_tor02":"M. Dr.Torsche, Grand Library","dun_tor04":"Mansion Dr.Torsche, Annex","fld_tor":"M. Dr.Torsche, Savage Garden","dun_tor_dr":"Laboratory of Dr.Torsche","dun_tor_boss":"Machinery Room of Dr.Torsche","dun_alq01":"Al Quelt Moreza, Nartex","dun_alq02":"Al Quelt Moreza, Arcade","dun_alq03":"Al Quelt Moreza, Parsonage","dun_alq03_sec":"Al Quelt Moreza, Parsonage","dun_alq04":"Rion Dungeon Corridor","dun_alq05":"Rion Dungeon Hollow","btl_alq02":"Rio Albi","dun_alq_boss":"Al Quelt Moreza Hollow","dun_ttr01":"Tetra Ruins, Grand Corridor","dun_ttr02":"Tetra Catacomb","dun_ttr03":"Tetra Golden Road","dun_ttr02_sec":"Tetra Catacomb","dun_ttr06":"Tetra Grand Chapel","dun_ttr_boss":"The Tetra Antiquities Room","dun_ptv01":"Porto Bello, The Deck","dun_ptv02":"Porto Bello, The Cabin","dun_ptv03":"Porto Bello, The Hold","dun_ptv02_sec":"Porto Bello, The Cabin","dun_ptv04":"Porto Bello, Hidden Deck","btl_ptv02":"Desolate Cliff of Porto Bello","btl_coim02":"Old Port of Coimbra","dun_ptv_boss":"Porto Bello, St. Cathrina Saloon","dun_ust01":"1F of Skeleton Dungeon","dun_ust02":"2F of Skeleton Dungeon","dun_ust04":"Ancient Skeleton Nest 1F","dun_ust03":"3F of Skeleton Dungeon","dun_ust01_sec":"1F of Skeleton Dungeon","dun_ust_boss":"The Room of the Dead","dun_ktv01":"Tower of Ice Wizard - 1F","dun_ktv04":"Tower of Ice Wizard - 2F","dun_ktv03":"Tower of Ice Wizard - 3F","dun_ktv05":"Tower of Ice Wizard - 5F","btl_ktv01":"Scorching Plateau","btl_ktv02":"Ferruccio Wall","btl_ktv03":"Katovic Snowfield","btl_ktv04":"Frozen Plain","btl_ktv05":"Snowfield of the Ice Wizard","btl_ktv05_tomb":"Distorted Time : Snowfield of the Ice Wizard","dun_ktv_boss":"Tower of Ice Wizard, Parlor of Novia","btl_tbk01":"Abertal","btl_tbk02":"Via Fluvial","btl_tbk03":"Deprimida Valley","dun_tbk01":"Capybara Plantation","dun_tbk02":"Mine Passage","dun_tbk_boss":"Tubkal Mine","dun_sil01":"Silent Maze - 1F","dun_sil02":"Silent Maze - 2F","dun_sil_boss":"Silent Maze Sanctuary","office_coim":"Pegadilla","office_reb":"Royal Guest House","office_auch":"Villa de Libertad","los_basic":"Los Toldos","office_reb_movie":"Royal Guest House","test_room":"Test Room-1","bah_basic":"Bahamar, Base Camp","bah_old":"Bahamar, House of Old Witch","bah_witchin":"Bahamar, Room of Witch","bah_witch":"Bahamar, House of Witch","btl_bah01":"Bahamar, Marshlands","btl_bah02":"Bahamar, Dark Swamp","btl_bah03":"Bahamar, Swamp of Eternity","btl_bah04":"Bahamar, Swamp of Peril","dun_bah01":"Bahamar, Cave 1F","dun_bah02":"Bahamar, Cave 2F","common_housein":"Ernesto's Cabin","dun_bah01_mission":"Bahamar, Grotto","dun_bah04":"Bahamar, Ancient Cave 1F","btl_bah05":"Bahamar, Forest of Prophet","btl_bah06":"Bahamar, Altar of Heaven","fld_gig":"Outside Gigante","btl_gig01":"Island of Fire","dun_gig_boss":"Inside Crater","gig_basic":"Port of Gigante","mission_bridge":"Royal Rumble","btl_sed01":"Tierra Putrefacta","dun_sed01":"Cabeza de Gigante","dun_sek02":"Corazon de Gigante","dun_sek03":"Interna de Gigante","dun_sek04":"Sacred Sedecram Dungeon","mission_liberty":"Liberty Colosseum, Event","dun_secret_hallway":"Tetra Hideout","btl_los01":"Tierra de los Muertos","btl_los02":"Deadlands Entrance","mission_los_01":"Deadlands","mission_poisonyard":"Poison Yard","mission_shadowtemple2":"Secret Temple","mission_clover":"El Antiguo Patrimonio","mission_factious01":"Tierra De La Sed","dun_secrettower01":"Secret Tower 1F","dun_secrettower02":"Secret Tower 3F","None":"None","mission_trinity_a":"The Dungeon first discovered by Ramiro","mission_arbremon":"Time Piece, Arbremon: HARD","mission_spotlight_b":"Battle in the Darkness","mission_latem":"Memory of Dilos Latemn","mission_lostship":"Secret Port of Carlos","mission_quarry":"Reboldoeux Stone Pit, Work Pit 2","mission_versus":"Duel Colosseum","mission_yageneh":"A Penitent Yeganeh","mission_versus2":"Altar Colosseum","mission_coim_basic":"An Absinian Warrior","mission_find_keep":"Real Criminal","mission_hellvally":"Valley of Hell","mission_lovidic":"Demon of the Sea, Loby Dick","mission_ramiro_trap":"Competing with Ramiro","mission_taylor":"Andre has gone crazy!! Andre Janzur","mission_cow01":"Protector of the Cows","mission_ttr_treasure":"Tetra Treasure Room","arena_lobby1":"Al Quelt Moreza Treasure Chamber","mission_dun_tor01":"Intruder Alert!","mission_coim_terrible":"Coimbra Showdown","mission_bad_apology":"A Path of Warrior to Humility 3: Unaccepted Apologies","mission_lascasas_bythesea":"Las Casas by the Sea","mission_epolite_tomb":"Tombstone of Epolite","mission_btl_ptv01":"Master","mission_tornado_reen":"Tornado Reen","mission_final_follower":"The First Disciple","mission_storm_bull":"A Bull Amidst the Storm","mission_tracer1":"Road to Independence 1","mission_wounded":"A Song of the Wounded","mission_tracer2":"Road to Independence 2","mission_auchpark":"Enhance Gun","mission_attackedbase":"Ustiur Base Camp Under Siege","mission_tyrannosaurus":"The Tyrannosaurus","mission_rescue":"Rescue","mission_confrontation":"Conflict","mission_brontosaurus":"The Frozen Megalosaur","mission_montoro":"Montoro","mission_awaytofarm":"The Way to the Farm","mission_legwork":"Investigation on Shopping Street","mission_evilchain":"Iron Chain of Vindictive Spirit","mission_fivetwins":"The Quintuplet Thieves","mission_sunflower":"Sunflower Dandelion Swamp Monkey","mission_thefortress":"NPC Strike Control","mission_reb01":"Stranger","mission_doghunt":"Dummy","fld_colony":"Round Stadium (World PVP)","mission_factious03":"Faction Arena","fld_battlerumbl":"Rumble Fight (Stadium)","bst_basic":"Escape","mission_bst02":"Barrol's Vow","mission_bst01":"Black Mask","btl_bst02":"Forbidden Rune Spell","bst_lab":"Unsought Fight","mission_interchange":"Weight Training","viron_basic":"A behind-the-scenes story","btl_viron00":"Black Knight","btl_viron01":"Show me the money!","dun_caslucifer03":"The Time Piece : Pharrel(1)","dun_lucifer01":"The Time Piece : Pharrel(2)","dun_lucifer02":"The Time Piece : Pharrel(3)","mission_btl_lucifer02":"Thing that she doesn't have.","dun_caslucifer02":"Rose dyed with black","dun_clocktower01":"Exi Pharrel","bst_basic02":"The smile of Wraith","mission_picnic":"100th challenge","dun_jaq_sub":"Valeria's Truth","mission_dun_sek03_b":"New Beast Corps3","dun_erc01":"New Beast Corps4","mission_bah_witch04":"Twisted Time","btl_cas01":"Truth of Castilla1","mission_tower_of_chaos":"Truth of Castilla2","dun_drangonlair":"Lunatic Jormongand","mission_novia_seal":"Tower of Ice Wizard","dun_pom_sewerage":"Freeday's Part time : part3","btl_lucifer02":"Rose Sister's Conflict","mission_los01":"Miracle exchange","mission_trinity_b":"Infinito Challenge","dun_erc_boss":"Infinito Challenge","dun_alkaboss":"Infinito Challenge","dun_secrettower_boss":"Infinito Challenge","mission_clocktower_boss":"Infinito Challenge","mission_nephthys":"Infinito Challenge","mission_btl_bah02":"Dark Swamp, Frogfish Hunting Ground : Hard","mission_jaq01":"Jaquin Basement Passage : Hard","mission_masung_cas03":"Demonic Medusa : Hard","mission_masung_cas02":"Demonic Minotauros : Hard","mission_masung_cas01":"Demonic Sphinx : Hard","dun_tor02_mission":"Demonic Dr.Torsche Dungeon Dungeon : Hard","mission_viron_curse":"Lift Cursed Pattern : Hard","dun_palace":"Chateau de Bourgogne : Hard","mission_secrettower01":"Secret Tower Dungeon : Hard","btl_bst01":"Citizen Rescue : Hard","mission_palace_02":"Secret Vault of Arsene : Hard","dun_alq06":"Al Quelt Moreza, Holy Water Chamber : Hard","btl_viron03":"Lost Glorious Time : Hard","mission_cas_mine":"Castilla, Mine : Hard","dun_ttr04":"Road of Avernus in Tetra : Hard","dun_tor00":"Dr.Torsche Dungeon : Hard","mission_elemetal_room":"Trinity Elemental Force : Hard","btl_lucifer01":"Lucifer, Secret Garden","dun_caslucifer01":"Lucifer, Banquet Hall","mission_shadowtemple":"Secret Temple","mission_trinity_c":"Trinity Lv.3","mission_spotlight_a":"Spotlight Lv.1","mission_spotlight_c":"Spotlight Lv.3","mission_highway":"Highway Lv.1","mission_jaq_que01":"Spirit of Jaquin","mission_jaq_que02":"Undead Soldiers","mission_resurrection_tachyon":"Resurrection of Takion","mission_plotter":"Conspiracy of Cherlyn","mission_bah_witch01":"House of Witch","mission_beataway":"Assault Jaquin.","mission_coldglove":"A Lady Who Wears a Glove","mission_violence":"Showdown in the Snowfield","mission_gig":"Ice Recluse","mission_btl_ktv02":"Ferruccio Wall Inspection","mission_dun_sek03_a":"Waiting Woman","mission_dun_sek02":"A Sense of Fate","reb_blksmith":"Secret Laboratory","mission_secrettower02":"Secret Tower 2F","mission_hothouse":"Gigante Greenhouse","mission_ProtectEggs":"Outside Gigante","dun_pycu01":"Hidden Mushroom Cave","btl_erc01":"Protect Errac","erc_basic":"Errac","mission_dun_star":"Mission: 13 Unknown Rooms","mission_clocktower":"Viron, the Clock Tower 1F","mission_rose":"Time Piece, Rose","mission_btl_lucifer01":"Time Piece, Beast Jurgen","mission_dun_lucifer02":"Time Piece, Cortes","dun_clocktower02_04":"Viron, Clock Tower B4F","dun_clocktower02_05":"Viron, Clock Tower B5F","dun_clocktower02_06":"Viron, Clock Tower B6F","dun_alka_fl01":"Tigres Prison B1F","dun_alka_fl02":"Tigres Prison B2F","dun_alka_fl03":"Tigres Prison B3F","dun_alka_fl04":"Tigres Prison B4F","dun_alka_fl05":"Tigres Prison B5F","dun_alka_fl06":"Tigres Prison B6F","dun_alka_fl07":"Tigres Prison B7F","dun_alka_fl08":"Tigres Prison B8F","dun_alka_fl09":"Tigres Prison B9F","btl_erc02":"Errac, Land of Night","cas_garrison":"Castilla, Base 1","btl_cas02":"Castilla, Temple","btl_viron02":"Viron, Crow Forest","reb_battle":"Faction War - Cite de Reboldoeux","auch_battle":"Faction War - City of Auch","coim_battle":"Faction War - Port of Coimbra","mission_viron_raven":"Butler of Castle Raven","mission_viron_crowforest":"Crow Forest","mission_viron_alley":"BackStreet Battle","mission_viron_cafe":"True Identity of Dean","mission_viron_market":"Misunderstanding","mission_clocktower_02":"Viron, the Clock Tower 7F","mission_ktv04_natalie01":"Master of Snowfield (1)","mission_ktv04_natalie02":"Attack in Snowfield","mission_viron_ludin":"Disappointed Ludin","mission_btl_viron00":"Mysterious Swordwoman","mission_dun_lucifer01":"Experiment of Cortes","mission_hunt":"Hunting","mission_viron_fahrel":"Counterattack of Admiral","mission_dun_lucifer02_2":"Rescue Exploration","mission_coim_seacafe":"Memory of Tora - Run away from home","bst_pub":"Red Hat","fld_bst01":"Kielce - Training Camp","fld_bst02":"Kielce - Training Camp (Night)","office_bst":"Bristia Government Ge.","bst_basic03":"Kielce, Martial Law","dun_clocktower02_02":"Viron, Clock Tower B2F","dun_clocktower02_03":"Viron, Clock Tower B3F","dun_clocktower02_07":"Viron, Clock Tower B7F","dun_clocktower02_08":"Viron, Clock Tower B8F","dun_clocktower02_09":"Viron, Clock Tower B9F","mission_ifarm02":"Servant of Oscuras","mission_caslucifer01_grandies":"Meeting with Grandies","fld_colony01":"Gigantes","mission_brunie_btl_tbk01":"Lost Relic of Tubkal : first key","mission_brunie_btl_tbk02":"Lost Relic of Tubkal : second key","mission_brunie_btl_tbk03":"Lost Relic of Tubkal : third key","mission_brunie_dun_tbk01":"Lost Relic of Tubkal : Antiquities Chamber","bedel_farm":"Bedel's Farm","mission_xmas_ktv":"Tower of the Ice Wizard for Christmas","bst_pinta_zone":"Vongole (Movie)","mission_duncasile01_2":"Mission : Imperium Arma Recapture(Expert)","cas_basic":"Castilla, Base 1","dun_sed04":"Sacred Sedecram Dungeon"}